i2b2model/__init__.py
i2b2model/data/__init__.py
i2b2model/data/i2b2codes.py
i2b2model/data/i2b2encountermapping.py
i2b2model/data/i2b2observationfact.py
i2b2model/data/i2b2patientdimension.py
i2b2model/data/i2b2patientmapping.py
i2b2model/data/i2b2visitdimension.py
i2b2model/metadata/__init__.py
i2b2model/metadata/commondimension.py
i2b2model/metadata/i2b2conceptdimension.py
i2b2model/metadata/i2b2modifierdimension.py
i2b2model/metadata/i2b2ontology.py
i2b2model/metadata/i2b2ontologyquery.py
i2b2model/metadata/i2b2ontologyvisualattributes.py
i2b2model/metadata/i2b2schemes.py
i2b2model/metadata/i2b2tableaccess.py
i2b2model/scripts/__init__.py
i2b2model/scripts/genconffile.py
i2b2model/scripts/removefacts.py
i2b2model/shared/__init__.py
i2b2model/shared/i2b2core.py
i2b2model/shared/listchunker.py
i2b2model/shared/tablenames.py
i2b2model/sqlsupport/__init__.py
i2b2model/sqlsupport/dbconnection.py
i2b2model/sqlsupport/file_aware_parser.py
i2b2model/sqlsupport/i2b2tables.py
i2b2model/sqlsupport/orderedset.py
i2b2model/sqlsupport/tablebase.py
i2b2model/testingutils/__init__.py
i2b2model/testingutils/base_test_case.py
i2b2model/testingutils/connection_helper.py
i2b2model/testingutils/crc_testcasebase.py
i2b2model/testingutils/script_test_base.py
i2b2model-0.2.6.dist-info/LICENSE.txt
i2b2model-0.2.6.dist-info/METADATA
i2b2model-0.2.6.dist-info/WHEEL
i2b2model-0.2.6.dist-info/top_level.txt
i2b2model-0.2.6.dist-info/RECORD
