Metadata-Version: 2.1
Name: i2b2model
Version: 0.2.6
Summary: i2b2 Model Wrapper
Home-page: https://github.com/BD2KOnFHIR/i2b2model
Author: Harold Solbrig
Author-email: solbrig.harold@mayo.edu
License: Apache 2.0
Platform: UNKNOWN
Classifier: Development Status :: 3 - Alpha
Classifier: Environment :: Console
Classifier: Intended Audience :: Healthcare Industry
Classifier: License :: OSI Approved :: Apache Software License
Classifier: Topic :: Database
Classifier: Programming Language :: Python :: 3.6
Requires-Dist: SQLAlchemy
Requires-Dist: psycopg2-binary
Requires-Dist: python-dateutil
Requires-Dist: dynprops (>=0.1.5)
